Metadata-Version: 2.1
Name: dataflows-tabulator
Version: 1.54.3
Summary: Consistent interface for stream reading and writing tabular data (csv/xls/json/etc)
Home-page: https://github.com/akariv/tabulator-py
Author: Open Knowledge Foundation
Author-email: info@okfn.org
License: MIT
Keywords: frictionless data
Classifier: Development Status :: 4 - Beta
Classifier: Environment :: Web Environment
Classifier: Intended Audience :: Developers
Classifier: License :: OSI Approved :: MIT License
Classifier: Operating System :: OS Independent
Classifier: Programming Language :: Python :: 2
Classifier: Programming Language :: Python :: 2.7
Classifier: Programming Language :: Python :: 3
Classifier: Programming Language :: Python :: 3.3
Classifier: Programming Language :: Python :: 3.4
Classifier: Programming Language :: Python :: 3.5
Classifier: Programming Language :: Python :: 3.6
Classifier: Programming Language :: Python :: 3.7
Classifier: Topic :: Internet :: WWW/HTTP :: Dynamic Content
Classifier: Topic :: Software Development :: Libraries :: Python Modules
License-File: LICENSE.md
Requires-Dist: six>=1.9
Requires-Dist: click>=6.0
Requires-Dist: requests>=2.8
Requires-Dist: chardet>=3.0
Requires-Dist: boto3>=1.9
Requires-Dist: unicodecsv>=0.14
Requires-Dist: ijson>=3.0.3
Requires-Dist: jsonlines>=1.1
Requires-Dist: sqlalchemy>=0.9.6
Requires-Dist: linear-tsv>=1.0
Requires-Dist: xlrd>=1.0
Requires-Dist: openpyxl>=2.6
Provides-Extra: datapackage
Requires-Dist: datapackage>=1.12; extra == "datapackage"
Provides-Extra: develop
Requires-Dist: mock; extra == "develop"
Requires-Dist: pylama; extra == "develop"
Requires-Dist: pytest; extra == "develop"
Requires-Dist: pytest-cov; extra == "develop"
Requires-Dist: moto[server]; extra == "develop"
Provides-Extra: ods
Requires-Dist: ezodf>=0.3; extra == "ods"
Requires-Dist: lxml>=3.0; extra == "ods"
Provides-Extra: html
Requires-Dist: pyquery<1.4.2; extra == "html"
Provides-Extra: cchardet
Requires-Dist: cchardet>=2.0; extra == "cchardet"
